{
  "openapi": "3.1.0",
  "info": {
    "title": "FastAPI",
    "version": "0.1.0"
  },
  "paths": {
    "/auth/signup": {
      "post": {
        "tags": [
          "auth"
        ],
        "summary": "Signup",
        "operationId": "signup_auth_signup_post",
        "requestBody": {
          "content": {
            "application/json": {
              "schema": {
                "$ref": "#/components/schemas/SignupSchema"
              }
            }
          },
          "required": true
        },
        "responses": {
          "200": {
            "description": "Successful Response",
            "content": {
              "application/json": {
                "schema": {
                  "$ref": "#/components/schemas/TokenSchema"
                }
              }
            }
          },
          "422": {
            "description": "Validation Error",
            "content": {
              "application/json": {
                "schema": {
                  "$ref": "#/components/schemas/HTTPValidationError"
                }
              }
            }
          }
        }
      }
    },
    "/auth/token": {
      "post": {
        "tags": [
          "auth"
        ],
        "summary": "Login For Access Token",
        "operationId": "login_for_access_token_auth_token_post",
        "requestBody": {
          "content": {
            "application/x-www-form-urlencoded": {
              "schema": {
                "$ref": "#/components/schemas/Body_login_for_access_token_auth_token_post"
              }
            }
          },
          "required": true
        },
        "responses": {
          "200": {
            "description": "Successful Response",
            "content": {
              "application/json": {
                "schema": {
                  "$ref": "#/components/schemas/TokenSchema"
                }
              }
            }
          },
          "422": {
            "description": "Validation Error",
            "content": {
              "application/json": {
                "schema": {
                  "$ref": "#/components/schemas/HTTPValidationError"
                }
              }
            }
          }
        }
      }
    },
    "/auth/google/login": {
      "get": {
        "tags": [
          "auth"
        ],
        "summary": "Google Login",
        "operationId": "google_login_auth_google_login_get",
        "responses": {
          "200": {
            "description": "Successful Response",
            "content": {
              "application/json": {
                "schema": {

                }
              }
            }
          }
        }
      }
    },
    "/auth/google/callback": {
      "get": {
        "tags": [
          "auth"
        ],
        "summary": "Google Callback",
        "operationId": "google_callback_auth_google_callback_get",
        "responses": {
          "200": {
            "description": "Successful Response",
            "content": {
              "application/json": {
                "schema": {
                  "$ref": "#/components/schemas/TokenSchema"
                }
              }
            }
          }
        }
      }
    },
    "/users/me": {
      "get": {
        "tags": [
          "users"
        ],
        "summary": "Me",
        "operationId": "me_users_me_get",
        "responses": {
          "200": {
            "description": "Successful Response",
            "content": {
              "application/json": {
                "schema": {
                  "$ref": "#/components/schemas/UserPublicSchema"
                }
              }
            }
          }
        },
        "security": [
          {
            "OAuth2PasswordBearer": []
          }
        ]
      },
      "patch": {
        "tags": [
          "users"
        ],
        "summary": "Update Me",
        "operationId": "update_me_users_me_patch",
        "requestBody": {
          "content": {
            "application/json": {
              "schema": {
                "$ref": "#/components/schemas/UserUpdateSchema"
              }
            }
          },
          "required": true
        },
        "responses": {
          "200": {
            "description": "Successful Response",
            "content": {
              "application/json": {
                "schema": {
                  "$ref": "#/components/schemas/UserPublicSchema"
                }
              }
            }
          },
          "422": {
            "description": "Validation Error",
            "content": {
              "application/json": {
                "schema": {
                  "$ref": "#/components/schemas/HTTPValidationError"
                }
              }
            }
          }
        },
        "security": [
          {
            "OAuth2PasswordBearer": []
          }
        ]
      }
    },
    "/users/{user_id}/follow": {
      "post": {
        "tags": [
          "users"
        ],
        "summary": "Follow User",
        "operationId": "follow_user_users__user_id__follow_post",
        "security": [
          {
            "OAuth2PasswordBearer": []
          }
        ],
        "parameters": [
          {
            "name": "user_id",
            "in": "path",
            "required": true,
            "schema": {
              "type": "integer",
              "title": "User Id"
            }
          }
        ],
        "responses": {
          "204": {
            "description": "Successful Response"
          },
          "422": {
            "description": "Validation Error",
            "content": {
              "application/json": {
                "schema": {
                  "$ref": "#/components/schemas/HTTPValidationError"
                }
              }
            }
          }
        }
      },
      "delete": {
        "tags": [
          "users"
        ],
        "summary": "Unfollow User",
        "operationId": "unfollow_user_users__user_id__follow_delete",
        "security": [
          {
            "OAuth2PasswordBearer": []
          }
        ],
        "parameters": [
          {
            "name": "user_id",
            "in": "path",
            "required": true,
            "schema": {
              "type": "integer",
              "title": "User Id"
            }
          }
        ],
        "responses": {
          "204": {
            "description": "Successful Response"
          },
          "422": {
            "description": "Validation Error",
            "content": {
              "application/json": {
                "schema": {
                  "$ref": "#/components/schemas/HTTPValidationError"
                }
              }
            }
          }
        }
      }
    },
    "/users/{user_id}/followers": {
      "get": {
        "tags": [
          "users"
        ],
        "summary": "Get User Followers",
        "operationId": "get_user_followers_users__user_id__followers_get",
        "parameters": [
          {
            "name": "user_id",
            "in": "path",
            "required": true,
            "schema": {
              "type": "integer",
              "title": "User Id"
            }
          }
        ],
        "responses": {
          "200": {
            "description": "Successful Response",
            "content": {
              "application/json": {
                "schema": {
                  "type": "array",
                  "items": {
                    "$ref": "#/components/schemas/UserPublicSchema"
                  },
                  "title": "Response Get User Followers Users  User Id  Followers Get"
                }
              }
            }
          },
          "422": {
            "description": "Validation Error",
            "content": {
              "application/json": {
                "schema": {
                  "$ref": "#/components/schemas/HTTPValidationError"
                }
              }
            }
          }
        }
      }
    },
    "/users/{user_id}/following": {
      "get": {
        "tags": [
          "users"
        ],
        "summary": "Get User Following",
        "operationId": "get_user_following_users__user_id__following_get",
        "parameters": [
          {
            "name": "user_id",
            "in": "path",
            "required": true,
            "schema": {
              "type": "integer",
              "title": "User Id"
            }
          }
        ],
        "responses": {
          "200": {
            "description": "Successful Response",
            "content": {
              "application/json": {
                "schema": {
                  "type": "array",
                  "items": {
                    "$ref": "#/components/schemas/UserPublicSchema"
                  },
                  "title": "Response Get User Following Users  User Id  Following Get"
                }
              }
            }
          },
          "422": {
            "description": "Validation Error",
            "content": {
              "application/json": {
                "schema": {
                  "$ref": "#/components/schemas/HTTPValidationError"
                }
              }
            }
          }
        }
      }
    },
    "/videos/create": {
      "post": {
        "tags": [
          "videos"
        ],
        "summary": "Create Video Generation Request",
        "operationId": "create_video_generation_request_videos_create_post",
        "requestBody": {
          "content": {
            "application/json": {
              "schema": {
                "$ref": "#/components/schemas/VideoGenerationCreateSchema"
              }
            }
          },
          "required": true
        },
        "responses": {
          "200": {
            "description": "Successful Response",
            "content": {
              "application/json": {
                "schema": {
                  "$ref": "#/components/schemas/VideoGenerationObjectSchema"
                }
              }
            }
          },
          "422": {
            "description": "Validation Error",
            "content": {
              "application/json": {
                "schema": {
                  "$ref": "#/components/schemas/HTTPValidationError"
                }
              }
            }
          }
        },
        "security": [
          {
            "OAuth2PasswordBearer": []
          }
        ]
      }
    },
    "/videos/generation/{generation_id}/publish": {
      "post": {
        "tags": [
          "videos"
        ],
        "summary": "Publish Generated Video",
        "operationId": "publish_generated_video_videos_generation__generation_id__publish_post",
        "security": [
          {
            "OAuth2PasswordBearer": []
          }
        ],
        "parameters": [
          {
            "name": "generation_id",
            "in": "path",
            "required": true,
            "schema": {
              "type": "integer",
              "title": "Generation Id"
            }
          }
        ],
        "responses": {
          "200": {
            "description": "Successful Response",
            "content": {
              "application/json": {
                "schema": {
                  "$ref": "#/components/schemas/VideoPublicSchema"
                }
              }
            }
          },
          "422": {
            "description": "Validation Error",
            "content": {
              "application/json": {
                "schema": {
                  "$ref": "#/components/schemas/HTTPValidationError"
                }
              }
            }
          }
        }
      }
    },
    "/videos/{video_id}": {
      "get": {
        "tags": [
          "videos"
        ],
        "summary": "Get Video",
        "operationId": "get_video_videos__video_id__get",
        "parameters": [
          {
            "name": "video_id",
            "in": "path",
            "required": true,
            "schema": {
              "type": "integer",
              "title": "Video Id"
            }
          }
        ],
        "responses": {
          "200": {
            "description": "Successful Response",
            "content": {
              "application/json": {
                "schema": {
                  "$ref": "#/components/schemas/VideoPublicSchema"
                }
              }
            }
          },
          "422": {
            "description": "Validation Error",
            "content": {
              "application/json": {
                "schema": {
                  "$ref": "#/components/schemas/HTTPValidationError"
                }
              }
            }
          }
        }
      },
      "delete": {
        "tags": [
          "videos"
        ],
        "summary": "Delete Video",
        "operationId": "delete_video_videos__video_id__delete",
        "security": [
          {
            "OAuth2PasswordBearer": []
          }
        ],
        "parameters": [
          {
            "name": "video_id",
            "in": "path",
            "required": true,
            "schema": {
              "type": "integer",
              "title": "Video Id"
            }
          }
        ],
        "responses": {
          "204": {
            "description": "Successful Response"
          },
          "422": {
            "description": "Validation Error",
            "content": {
              "application/json": {
                "schema": {
                  "$ref": "#/components/schemas/HTTPValidationError"
                }
              }
            }
          }
        }
      }
    },
    "/videos/user/videos": {
      "get": {
        "tags": [
          "videos"
        ],
        "summary": "Get User Videos",
        "operationId": "get_user_videos_videos_user_videos_get",
        "responses": {
          "200": {
            "description": "Successful Response",
            "content": {
              "application/json": {
                "schema": {
                  "items": {
                    "$ref": "#/components/schemas/VideoPublicSchema"
                  },
                  "type": "array",
                  "title": "Response Get User Videos Videos User Videos Get"
                }
              }
            }
          }
        },
        "security": [
          {
            "OAuth2PasswordBearer": []
          }
        ]
      }
    },
    "/feed/": {
      "get": {
        "tags": [
          "feed"
        ],
        "summary": "Get Feed",
        "operationId": "get_feed_feed__get",
        "responses": {
          "200": {
            "description": "Successful Response",
            "content": {
              "application/json": {
                "schema": {
                  "$ref": "#/components/schemas/FeedSchema"
                }
              }
            }
          }
        },
        "security": [
          {
            "OAuth2PasswordBearer": []
          }
        ]
      }
    },
    "/interactions/{video_id}/like": {
      "post": {
        "tags": [
          "user_interactions"
        ],
        "summary": "Like Video",
        "operationId": "like_video_interactions__video_id__like_post",
        "security": [
          {
            "OAuth2PasswordBearer": []
          }
        ],
        "parameters": [
          {
            "name": "video_id",
            "in": "path",
            "required": true,
            "schema": {
              "type": "integer",
              "title": "Video Id"
            }
          }
        ],
        "responses": {
          "201": {
            "description": "Successful Response",
            "content": {
              "application/json": {
                "schema": {

                }
              }
            }
          },
          "422": {
            "description": "Validation Error",
            "content": {
              "application/json": {
                "schema": {
                  "$ref": "#/components/schemas/HTTPValidationError"
                }
              }
            }
          }
        }
      },
      "delete": {
        "tags": [
          "user_interactions"
        ],
        "summary": "Unlike Video",
        "operationId": "unlike_video_interactions__video_id__like_delete",
        "security": [
          {
            "OAuth2PasswordBearer": []
          }
        ],
        "parameters": [
          {
            "name": "video_id",
            "in": "path",
            "required": true,
            "schema": {
              "type": "integer",
              "title": "Video Id"
            }
          }
        ],
        "responses": {
          "204": {
            "description": "Successful Response"
          },
          "422": {
            "description": "Validation Error",
            "content": {
              "application/json": {
                "schema": {
                  "$ref": "#/components/schemas/HTTPValidationError"
                }
              }
            }
          }
        }
      }
    },
    "/interactions/{video_id}/comment": {
      "post": {
        "tags": [
          "user_interactions"
        ],
        "summary": "Post Comment",
        "operationId": "post_comment_interactions__video_id__comment_post",
        "security": [
          {
            "OAuth2PasswordBearer": []
          }
        ],
        "parameters": [
          {
            "name": "video_id",
            "in": "path",
            "required": true,
            "schema": {
              "type": "integer",
              "title": "Video Id"
            }
          }
        ],
        "requestBody": {
          "required": true,
          "content": {
            "application/json": {
              "schema": {
                "$ref": "#/components/schemas/PostCommentSchema"
              }
            }
          }
        },
        "responses": {
          "201": {
            "description": "Successful Response",
            "content": {
              "application/json": {
                "schema": {
                  "$ref": "#/components/schemas/CommentSchema"
                }
              }
            }
          },
          "422": {
            "description": "Validation Error",
            "content": {
              "application/json": {
                "schema": {
                  "$ref": "#/components/schemas/HTTPValidationError"
                }
              }
            }
          }
        }
      }
    },
    "/interactions/{video_id}/comments": {
      "get": {
        "tags": [
          "user_interactions"
        ],
        "summary": "Get Comments",
        "operationId": "get_comments_interactions__video_id__comments_get",
        "parameters": [
          {
            "name": "video_id",
            "in": "path",
            "required": true,
            "schema": {
              "type": "integer",
              "title": "Video Id"
            }
          }
        ],
        "responses": {
          "200": {
            "description": "Successful Response",
            "content": {
              "application/json": {
                "schema": {
                  "type": "array",
                  "items": {
                    "$ref": "#/components/schemas/CommentSchema"
                  },
                  "title": "Response Get Comments Interactions  Video Id  Comments Get"
                }
              }
            }
          },
          "422": {
            "description": "Validation Error",
            "content": {
              "application/json": {
                "schema": {
                  "$ref": "#/components/schemas/HTTPValidationError"
                }
              }
            }
          }
        }
      }
    },
    "/interactions/comment/{comment_id}": {
      "delete": {
        "tags": [
          "user_interactions"
        ],
        "summary": "Delete Comment",
        "operationId": "delete_comment_interactions_comment__comment_id__delete",
        "security": [
          {
            "OAuth2PasswordBearer": []
          }
        ],
        "parameters": [
          {
            "name": "comment_id",
            "in": "path",
            "required": true,
            "schema": {
              "type": "integer",
              "title": "Comment Id"
            }
          }
        ],
        "responses": {
          "204": {
            "description": "Successful Response"
          },
          "422": {
            "description": "Validation Error",
            "content": {
              "application/json": {
                "schema": {
                  "$ref": "#/components/schemas/HTTPValidationError"
                }
              }
            }
          }
        }
      }
    },
    "/": {
      "get": {
        "summary": "Root",
        "operationId": "root__get",
        "responses": {
          "200": {
            "description": "Successful Response",
            "content": {
              "application/json": {
                "schema": {

                }
              }
            }
          }
        }
      }
    },
    "/home": {
      "get": {
        "summary": "Home",
        "operationId": "home_home_get",
        "responses": {
          "200": {
            "description": "Successful Response",
            "content": {
              "text/html": {
                "schema": {
                  "type": "string"
                }
              }
            }
          }
        }
      }
    },
    "/ws/notify": {
      "post": {
        "summary": "Websocket Notify",
        "operationId": "websocket_notify_ws_notify_post",
        "requestBody": {
          "content": {
            "application/json": {
              "schema": {
                "additionalProperties": true,
                "type": "object",
                "title": "Payload"
              }
            }
          },
          "required": true
        },
        "responses": {
          "200": {
            "description": "Successful Response",
            "content": {
              "application/json": {
                "schema": {

                }
              }
            }
          },
          "422": {
            "description": "Validation Error",
            "content": {
              "application/json": {
                "schema": {
                  "$ref": "#/components/schemas/HTTPValidationError"
                }
              }
            }
          }
        }
      }
    }
  },
  "components": {
    "schemas": {
      "Body_login_for_access_token_auth_token_post": {
        "properties": {
          "grant_type": {
            "anyOf": [
              {
                "type": "string",
                "pattern": "^password$"
              },
              {
                "type": "null"
              }
            ],
            "title": "Grant Type"
          },
          "username": {
            "type": "string",
            "title": "Username"
          },
          "password": {
            "type": "string",
            "format": "password",
            "title": "Password"
          },
          "scope": {
            "type": "string",
            "title": "Scope",
            "default": ""
          },
          "client_id": {
            "anyOf": [
              {
                "type": "string"
              },
              {
                "type": "null"
              }
            ],
            "title": "Client Id"
          },
          "client_secret": {
            "anyOf": [
              {
                "type": "string"
              },
              {
                "type": "null"
              }
            ],
            "format": "password",
            "title": "Client Secret"
          }
        },
        "type": "object",
        "required": [
          "username",
          "password"
        ],
        "title": "Body_login_for_access_token_auth_token_post"
      },
      "CommentSchema": {
        "properties": {
          "video_id": {
            "type": "integer",
            "title": "Video Id"
          },
          "content": {
            "type": "string",
            "title": "Content"
          },
          "parent_comment_id": {
            "anyOf": [
              {
                "type": "integer"
              },
              {
                "type": "null"
              }
            ],
            "title": "Parent Comment Id"
          },
          "created_at": {
            "anyOf": [
              {
                "type": "string",
                "format": "date-time"
              },
              {
                "type": "null"
              }
            ],
            "title": "Created At"
          }
        },
        "type": "object",
        "required": [
          "video_id",
          "content"
        ],
        "title": "CommentSchema"
      },
      "FeedItemSchema": {
        "properties": {
          "video_id": {
            "type": "integer",
            "title": "Video Id"
          },
          "owner_username": {
            "type": "string",
            "title": "Owner Username"
          },
          "owner_profile_pic": {
            "anyOf": [
              {
                "type": "string"
              },
              {
                "type": "null"
              }
            ],
            "title": "Owner Profile Pic"
          },
          "caption": {
            "anyOf": [
              {
                "type": "string"
              },
              {
                "type": "null"
              }
            ],
            "title": "Caption"
          },
          "video_url": {
            "anyOf": [
              {
                "type": "string"
              },
              {
                "type": "null"
              }
            ],
            "title": "Video Url"
          },
          "thumbnail_url": {
            "anyOf": [
              {
                "type": "string"
              },
              {
                "type": "null"
              }
            ],
            "title": "Thumbnail Url"
          },
          "likes_count": {
            "type": "integer",
            "title": "Likes Count",
            "default": 0
          },
          "comments_count": {
            "type": "integer",
            "title": "Comments Count",
            "default": 0
          },
          "is_liked_by_user": {
            "type": "boolean",
            "title": "Is Liked By User",
            "default": false
          },
          "created_at": {
            "anyOf": [
              {
                "type": "string"
              },
              {
                "type": "null"
              }
            ],
            "title": "Created At"
          }
        },
        "type": "object",
        "required": [
          "video_id",
          "owner_username"
        ],
        "title": "FeedItemSchema"
      },
      "FeedSchema": {
        "properties": {
          "items": {
            "anyOf": [
              {
                "items": {
                  "$ref": "#/components/schemas/FeedItemSchema"
                },
                "type": "array"
              },
              {
                "type": "null"
              }
            ],
            "title": "Items",
            "default": []
          },
          "next_page_token": {
            "anyOf": [
              {
                "type": "string"
              },
              {
                "type": "null"
              }
            ],
            "title": "Next Page Token"
          }
        },
        "type": "object",
        "title": "FeedSchema"
      },
      "HTTPValidationError": {
        "properties": {
          "detail": {
            "items": {
              "$ref": "#/components/schemas/ValidationError"
            },
            "type": "array",
            "title": "Detail"
          }
        },
        "type": "object",
        "title": "HTTPValidationError"
      },
      "PostCommentSchema": {
        "properties": {
          "video_id": {
            "type": "integer",
            "title": "Video Id"
          },
          "comment_text": {
            "type": "string",
            "title": "Comment Text"
          },
          "parent_comment_id": {
            "anyOf": [
              {
                "type": "integer"
              },
              {
                "type": "null"
              }
            ],
            "title": "Parent Comment Id"
          }
        },
        "type": "object",
        "required": [
          "video_id",
          "comment_text"
        ],
        "title": "PostCommentSchema"
      },
      "SignupSchema": {
        "properties": {
          "email": {
            "type": "string",
            "format": "email",
            "title": "Email"
          },
          "username": {
            "type": "string",
            "maxLength": 30,
            "minLength": 3,
            "title": "Username"
          },
          "password": {
            "type": "string",
            "maxLength": 256,
            "minLength": 8,
            "title": "Password"
          }
        },
        "type": "object",
        "required": [
          "email",
          "username",
          "password"
        ],
        "title": "SignupSchema"
      },
      "TokenSchema": {
        "properties": {
          "access_token": {
            "type": "string",
            "title": "Access Token"
          },
          "token_type": {
            "type": "string",
            "title": "Token Type",
            "default": "bearer"
          }
        },
        "type": "object",
        "required": [
          "access_token"
        ],
        "title": "TokenSchema"
      },
      "UserPublicSchema": {
        "properties": {
          "id": {
            "type": "integer",
            "title": "Id"
          },
          "email": {
            "type": "string",
            "format": "email",
            "title": "Email"
          },
          "username": {
            "type": "string",
            "title": "Username"
          },
          "bio": {
            "anyOf": [
              {
                "type": "string"
              },
              {
                "type": "null"
              }
            ],
            "title": "Bio"
          },
          "profile_pic": {
            "anyOf": [
              {
                "type": "string"
              },
              {
                "type": "null"
              }
            ],
            "title": "Profile Pic"
          }
        },
        "type": "object",
        "required": [
          "id",
          "email",
          "username"
        ],
        "title": "UserPublicSchema"
      },
      "UserUpdateSchema": {
        "properties": {
          "username": {
            "anyOf": [
              {
                "type": "string"
              },
              {
                "type": "null"
              }
            ],
            "title": "Username"
          },
          "bio": {
            "anyOf": [
              {
                "type": "string"
              },
              {
                "type": "null"
              }
            ],
            "title": "Bio"
          },
          "profile_pic": {
            "anyOf": [
              {
                "type": "string"
              },
              {
                "type": "null"
              }
            ],
            "title": "Profile Pic"
          }
        },
        "type": "object",
        "title": "UserUpdateSchema"
      },
      "ValidationError": {
        "properties": {
          "loc": {
            "items": {
              "anyOf": [
                {
                  "type": "string"
                },
                {
                  "type": "integer"
                }
              ]
            },
            "type": "array",
            "title": "Location"
          },
          "msg": {
            "type": "string",
            "title": "Message"
          },
          "type": {
            "type": "string",
            "title": "Error Type"
          }
        },
        "type": "object",
        "required": [
          "loc",
          "msg",
          "type"
        ],
        "title": "ValidationError"
      },
      "VideoGenerationCreateSchema": {
        "properties": {
          "prompt": {
            "type": "string",
            "title": "Prompt"
          }
        },
        "type": "object",
        "required": [
          "prompt"
        ],
        "title": "VideoGenerationCreateSchema"
      },
      "VideoGenerationObjectSchema": {
        "properties": {
          "id": {
            "anyOf": [
              {
                "type": "integer"
              },
              {
                "type": "null"
              }
            ],
            "title": "Id"
          },
          "video_id": {
            "anyOf": [
              {
                "type": "integer"
              },
              {
                "type": "null"
              }
            ],
            "title": "Video Id"
          },
          "prompt": {
            "anyOf": [
              {
                "type": "string"
              },
              {
                "type": "null"
              }
            ],
            "title": "Prompt"
          },
          "file_path": {
            "anyOf": [
              {
                "type": "string"
              },
              {
                "type": "null"
              }
            ],
            "title": "File Path"
          },
          "status": {
            "anyOf": [
              {
                "type": "string"
              },
              {
                "type": "null"
              }
            ],
            "title": "Status"
          },
          "created_at": {
            "anyOf": [
              {
                "type": "string",
                "format": "date-time"
              },
              {
                "type": "null"
              }
            ],
            "title": "Created At"
          },
          "updated_at": {
            "anyOf": [
              {
                "type": "string",
                "format": "date-time"
              },
              {
                "type": "null"
              }
            ],
            "title": "Updated At"
          }
        },
        "type": "object",
        "title": "VideoGenerationObjectSchema"
      },
      "VideoPublicSchema": {
        "properties": {
          "id": {
            "anyOf": [
              {
                "type": "integer"
              },
              {
                "type": "null"
              }
            ],
            "title": "Id"
          },
          "owner_id": {
            "anyOf": [
              {
                "type": "integer"
              },
              {
                "type": "null"
              }
            ],
            "title": "Owner Id"
          },
          "status": {
            "anyOf": [
              {
                "type": "string"
              },
              {
                "type": "null"
              }
            ],
            "title": "Status"
          },
          "caption": {
            "anyOf": [
              {
                "type": "string"
              },
              {
                "type": "null"
              }
            ],
            "title": "Caption"
          },
          "video_url": {
            "anyOf": [
              {
                "type": "string"
              },
              {
                "type": "null"
              }
            ],
            "title": "Video Url"
          },
          "thumbnail_url": {
            "anyOf": [
              {
                "type": "string"
              },
              {
                "type": "null"
              }
            ],
            "title": "Thumbnail Url"
          },
          "likes_count": {
            "anyOf": [
              {
                "type": "integer"
              },
              {
                "type": "null"
              }
            ],
            "title": "Likes Count",
            "default": 0
          },
          "comments_count": {
            "anyOf": [
              {
                "type": "integer"
              },
              {
                "type": "null"
              }
            ],
            "title": "Comments Count",
            "default": 0
          },
          "created_at": {
            "anyOf": [
              {
                "type": "string",
                "format": "date-time"
              },
              {
                "type": "null"
              }
            ],
            "title": "Created At"
          }
        },
        "type": "object",
        "title": "VideoPublicSchema"
      }
    },
    "securitySchemes": {
      "OAuth2PasswordBearer": {
        "type": "oauth2",
        "flows": {
          "password": {
            "scopes": {

            },
            "tokenUrl": "auth/token"
          }
        }
      }
    }
  }
}